Metadata-Version: 1.1
Name: scythe
Version: 0.1a1
Summary: Find best matching set of transcripts for one-to-one orthologous genes from two or more species
Home-page: UNKNOWN
Author: Janina Mass
Author-email: janina.mass@hhu.de
License: GPLv3
Platform: UNKNOWN
Classifier: Topic :: Scientific/Engineering :: Bio-Informatics
